{
  "$schema": "https://json-schema.org/draft/2019-09/schema",
  "$id": "/prerequisites/single/RacePrerequisite.schema.json",
  "$defs": {
    "RacePrerequisite": {
      "title": "Race Prerequisite",
      "description": "Requires a specific race or one of a specific set of races. You can also\nprovide an object to say whether the hero must meet one of the races or\nif the entry does not allow one of the races.",
      "type": "object",
      "properties": {
        "id": {
          "description": "The race's identifier.",
          "$ref": "../../_Identifier.schema.json#/$defs/RaceIdentifier"
        },
        "active": {
          "type": "boolean"
        },
        "display_option": {
          "$ref": "../DisplayOption.schema.json#/$defs/DisplayOption"
        }
      },
      "required": [
        "id",
        "active"
      ],
      "additionalProperties": false
    }
  }
}
